yrequests/__init__.py
yrequests-0.1.0.dist-info/LICENSE.txt
yrequests-0.1.0.dist-info/METADATA
yrequests-0.1.0.dist-info/RECORD
yrequests-0.1.0.dist-info/WHEEL
yrequests-0.1.0.dist-info/top_level.txt
