Metadata-Version: 2.1
Name: yrequests
Version: 0.1.0
Summary: A very simple module for HTTP/1.1 requests.
Home-page: https://github.com/yoshiodeveloper/yrequests
Author: Yoshio Iwamoto
Author-email: yoshiodeveloper@gmail.com
License: UNKNOWN
Project-URL: Bug Reports, https://github.com/yoshiodeveloper/yrequests/issues
Project-URL: Source, https://github.com/yoshiodeveloper/yrequests
Platform: UNKNOWN
Classifier: Development Status :: 4 - Beta
Classifier: Intended Audience :: Developers
Classifier: Topic :: Utilities
Classifier: License :: OSI Approved :: MIT License
Classifier: Programming Language :: Python :: 2.6
Classifier: Programming Language :: Python :: 2.7
Classifier: Programming Language :: Python :: 3
Classifier: Programming Language :: Python :: 3.0
Classifier: Programming Language :: Python :: 3.1
Classifier: Programming Language :: Python :: 3.2
Classifier: Programming Language :: Python :: 3.4
Classifier: Programming Language :: Python :: 3.5
Classifier: Programming Language :: Python :: 3.6
Classifier: Programming Language :: Python :: 3.7
Requires-Dist: requests
Requires-Dist: future; python_version < "3"
